kblite/__init__.py
kblite/base.py
kblite/loader.py
kblite/models.py
kblite/triplet.py
kblite/vocab.py
kblite/conceptnet/__init__.py
kblite/conceptnet/base.py
kblite/conceptnet/concept.py
kblite/conceptnet/csv.py
kblite/conceptnet/namepsace.py
kblite/conceptnet/relation.py
kblite/conceptnet/uri.py
kblite-0.0.1.dist-info/METADATA
kblite-0.0.1.dist-info/WHEEL
kblite-0.0.1.dist-info/licenses/LICENSE
kblite-0.0.1.dist-info/RECORD
