Metadata-Version: 2.4
Name: kblite
Version: 0.0.1
Summary: A SQLite-based interface for Knowledge Bases
Project-URL: Homepage, https://github.com/ysenarath/kblite
Project-URL: Repository, https://github.com/ysenarath/kblite
Project-URL: Dataset, https://huggingface.co/datasets/ysenarath/conceptnet-sqlite
Author: Yasas Senarath
License: MIT License
License-File: LICENSE
Keywords: conceptnet,knowledge-base,sqlite
Classifier: Development Status :: 3 - Alpha
Classifier: Intended Audience :: Science/Research
Classifier: License :: OSI Approved :: MIT License
Classifier: Programming Language :: Python :: 3
Classifier: Programming Language :: Python :: 3.7
Classifier: Programming Language :: Python :: 3.8
Classifier: Programming Language :: Python :: 3.9
Classifier: Programming Language :: Python :: 3.10
Classifier: Programming Language :: Python :: 3.11
Classifier: Topic :: Scientific/Engineering :: Artificial Intelligence
Requires-Python: >=3.7
Requires-Dist: datasets
Requires-Dist: huggingface-hub
Requires-Dist: nightjar
Requires-Dist: numpy
Requires-Dist: orjson
Requires-Dist: plyvel-ci
Requires-Dist: rdflib
Requires-Dist: sqlalchemy
Requires-Dist: torch
Requires-Dist: tqdm
Requires-Dist: wordfreq
